drmock/__init__.py
drmock/_debug.py
drmock/commandline.py
drmock/generator.py
drmock/overload.py
drmock/translator.py
drmock/types.py
drmock/utils.py
drmock_generator-0.6.0.dist-info/METADATA
drmock_generator-0.6.0.dist-info/WHEEL
drmock_generator-0.6.0.dist-info/entry_points.txt
drmock_generator-0.6.0.dist-info/top_level.txt
drmock_generator-0.6.0.dist-info/RECORD
