Metadata-Version: 2.1
Name: drmock-generator
Version: 0.6.0
Summary: C++ mock object generator
Home-page: UNKNOWN
Author: Malte Kliemann, Ole Kliemann
License: GLP-3.0-or-later
Platform: UNKNOWN
Requires-Python: >=3.7
Requires-Dist: clang (>=11.0)
